marsdariancalendar.py
marsdariancalendar-1.0.0.dist-info/licenses/LICENSE
marsdariancalendar-1.0.0.dist-info/METADATA
marsdariancalendar-1.0.0.dist-info/WHEEL
marsdariancalendar-1.0.0.dist-info/top_level.txt
marsdariancalendar-1.0.0.dist-info/RECORD
